tracardi_maxmind_geolite2/__init__.py
tracardi_maxmind_geolite2/plugin.py
tracardi_maxmind_geolite2/test.py
tracardi_maxmind_geolite2/model/__init__.py
tracardi_maxmind_geolite2/model/maxmind_geolite2_client.py
tracardi_maxmind_geolite2/model/__pycache__/__init__.cpython-38.pyc
tracardi_maxmind_geolite2/model/__pycache__/maxmind_geolite2_client.cpython-38.pyc
tracardi_maxmind_geolite2-0.6.0.dist-info/LICENSE.md
tracardi_maxmind_geolite2-0.6.0.dist-info/METADATA
tracardi_maxmind_geolite2-0.6.0.dist-info/WHEEL
tracardi_maxmind_geolite2-0.6.0.dist-info/top_level.txt
tracardi_maxmind_geolite2-0.6.0.dist-info/RECORD
