Metadata-Version: 2.1
Name: tracardi-maxmind-geolite2
Version: 0.6.0
Summary: This plugins connect to maxmind geolite2 service and retrieve location data.
Home-page: UNKNOWN
Author: Risto Kowaczewski
Author-email: risto.kowaczewski@gmail.com
License: UNKNOWN
Keywords: tracardi,plugin
Platform: UNKNOWN
Classifier: Programming Language :: Python :: 3
Classifier: License :: OSI Approved :: MIT License
Classifier: Operating System :: OS Independent
Requires-Python: >=3.8
License-File: LICENSE.md
Requires-Dist: tracardi-plugin-sdk (>=0.6.21)
Requires-Dist: tracardi
Requires-Dist: tracardi-dot-notation
Requires-Dist: geoip2 (~=4.2.0)
